docker_vuln_controller/client.py
docker_vuln_controller/main.py
docker_vuln_node/main.py
docker_vuln_node/node.py
docker_vuln_runner/helper.py
docker_vuln_runner/hosts.py
docker_vuln_runner/main.py
docker_vuln_runner/message.py
docker_vuln_runner/vuln.py
vuln_runner-0.1.6.dist-info/LICENSE.md
vuln_runner-0.1.6.dist-info/METADATA
vuln_runner-0.1.6.dist-info/WHEEL
vuln_runner-0.1.6.dist-info/entry_points.txt
vuln_runner-0.1.6.dist-info/RECORD
