Metadata-Version: 2.1
Name: vuln-runner
Version: 0.1.6
Summary: A Docker runner for docker-based vulnerable environments.
Author: SecSI
Author-email: dev@secsi.io
Requires-Python: >=3.8,<4.0
Classifier: Programming Language :: Python :: 3
Classifier: Programming Language :: Python :: 3.8
Classifier: Programming Language :: Python :: 3.9
Classifier: Programming Language :: Python :: 3.10
Classifier: Programming Language :: Python :: 3.11
Classifier: Programming Language :: Python :: 3.12
Requires-Dist: gitpython (>=3.1.29,<4.0.0)
Requires-Dist: python-on-whales (==0.68.0)
Requires-Dist: pyyaml (>=6.0,<7.0)
Requires-Dist: typer (==0.9.0)
